flask_sec_fetch_csrf/extension.py
flask_sec_fetch_csrf/exceptions.py
flask_sec_fetch_csrf/__init__.py
flask_sec_fetch_csrf-0.2.0.dist-info/WHEEL
flask_sec_fetch_csrf-0.2.0.dist-info/METADATA
flask_sec_fetch_csrf-0.2.0.dist-info/RECORD
