Metadata-Version: 2.4
Name: flask-sec-fetch-csrf
Version: 0.2.0
Summary: CSRF protection for Flask using Sec-Fetch-Site header
Keywords: flask,csrf,security,sec-fetch-site,fetch-metadata
Author: Sharoon Thomas
Author-email: Sharoon Thomas <sharoon.thomas@fulfil.io>
License-Expression: BSD-3-Clause
Classifier: Development Status :: 4 - Beta
Classifier: Environment :: Web Environment
Classifier: Framework :: Flask
Classifier: Intended Audience :: Developers
Classifier: License :: OSI Approved :: BSD License
Classifier: Operating System :: OS Independent
Classifier: Programming Language :: Python :: 3
Classifier: Programming Language :: Python :: 3.10
Classifier: Programming Language :: Python :: 3.11
Classifier: Programming Language :: Python :: 3.12
Classifier: Programming Language :: Python :: 3.13
Classifier: Programming Language :: Python :: 3.14
Classifier: Topic :: Internet :: WWW/HTTP :: WSGI :: Middleware
Classifier: Topic :: Security
Requires-Dist: flask>=2.0
Requires-Dist: pytest>=7.0 ; extra == 'dev'
Requires-Dist: pytest-cov>=4.0 ; extra == 'dev'
Requires-Dist: ruff>=0.1 ; extra == 'dev'
Requires-Python: >=3.10
Project-URL: Documentation, https://github.com/fulfilio/flask-sec-fetch-csrf#readme
Project-URL: Homepage, https://github.com/fulfilio/flask-sec-fetch-csrf
Project-URL: Issues, https://github.com/fulfilio/flask-sec-fetch-csrf/issues
Project-URL: Repository, https://github.com/fulfilio/flask-sec-fetch-csrf
Provides-Extra: dev
